nlp_dedup/__init__.py
nlp_dedup/cli.py
nlp_dedup/deduper.py
nlp_dedup/types.py
nlp_dedup/utils.py
nlp_dedup-0.1.2.dist-info/LICENSE
nlp_dedup-0.1.2.dist-info/METADATA
nlp_dedup-0.1.2.dist-info/WHEEL
nlp_dedup-0.1.2.dist-info/entry_points.txt
nlp_dedup-0.1.2.dist-info/RECORD
