Metadata-Version: 2.1
Name: nlp-dedup
Version: 0.1.2
Summary: Remove duplicates and near-duplicates from text corpora, no matter the scale.
License: MIT
Author: Dan Saattrup Nielsen
Author-email: dan.nielsen@alexandra.dk
Requires-Python: >=3.8,<4.0
Classifier: License :: OSI Approved :: MIT License
Classifier: Programming Language :: Python :: 3
Classifier: Programming Language :: Python :: 3.8
Classifier: Programming Language :: Python :: 3.9
Classifier: Programming Language :: Python :: 3.10
Classifier: Programming Language :: Python :: 3.11
Requires-Dist: datasketch (>=1.5.8,<2.0.0)
Requires-Dist: joblib (>=1.2.0,<2.0.0)
Requires-Dist: more-itertools (>=9.0.0,<10.0.0)
Requires-Dist: tqdm (>=4.64.1,<5.0.0)
